{
    "os": "Linux-6.5.0-21-generic-x86_64-with-glibc2.35",
    "python": "3.9.18",
    "heartbeatAt": "2024-02-28T09:43:24.203878",
    "startedAt": "2024-02-28T09:43:22.898761",
    "docker": null,
    "cuda": null,
    "args": [
        "--diffusion_mode",
        "sample"
    ],
    "state": "running",
    "program": "/home/sehwan/MIIL/CAL-Refactoring/dlt/main.py",
    "codePathLocal": "main.py",
    "codePath": "main.py",
    "host": "sehwan--Ubuntu",
    "username": "sehwan",
    "executable": "/home/sehwan/anaconda3/envs/CAL/bin/python",
    "cpu_count": 16,
    "cpu_count_logical": 24,
    "cpu_freq": {
        "current": 1321.8294166666665,
        "min": 800.0,
        "max": 4950.0
    },
    "cpu_freq_per_core": [
        {
            "current": 1413.504,
            "min": 800.0,
            "max": 5300.0
        },
        {
            "current": 1567.983,
            "min": 800.0,
            "max": 5300.0
        },
        {
            "current": 1866.071,
            "min": 800.0,
            "max": 5300.0
        },
        {
            "current": 800.0,
            "min": 800.0,
            "max": 5300.0
        },
        {
            "current": 1424.052,
            "min": 800.0,
            "max": 5300.0
        },
        {
            "current": 800.0,
            "min": 800.0,
            "max": 5300.0
        },
        {
            "current": 1416.334,
            "min": 800.0,
            "max": 5300.0
        },
        {
            "current": 800.0,
            "min": 800.0,
            "max": 5300.0
        },
        {
            "current": 1612.263,
            "min": 800.0,
            "max": 5400.0
        },
        {
            "current": 1510.458,
            "min": 800.0,
            "max": 5400.0
        },
        {
            "current": 1643.187,
            "min": 800.0,
            "max": 5400.0
        },
        {
            "current": 1407.612,
            "min": 800.0,
            "max": 5400.0
        },
        {
            "current": 1427.439,
            "min": 800.0,
            "max": 5300.0
        },
        {
            "current": 800.0,
            "min": 800.0,
            "max": 5300.0
        },
        {
            "current": 1430.356,
            "min": 800.0,
            "max": 5300.0
        },
        {
            "current": 800.0,
            "min": 800.0,
            "max": 5300.0
        },
        {
            "current": 2252.622,
            "min": 800.0,
            "max": 4200.0
        },
        {
            "current": 800.0,
            "min": 800.0,
            "max": 4200.0
        },
        {
            "current": 800.0,
            "min": 800.0,
            "max": 4200.0
        },
        {
            "current": 800.0,
            "min": 800.0,
            "max": 4200.0
        },
        {
            "current": 800.0,
            "min": 800.0,
            "max": 4200.0
        },
        {
            "current": 800.0,
            "min": 800.0,
            "max": 4200.0
        },
        {
            "current": 800.0,
            "min": 800.0,
            "max": 4200.0
        },
        {
            "current": 800.0,
            "min": 800.0,
            "max": 4200.0
        }
    ],
    "disk": {
        "/": {
            "total": 457.3268280029297,
            "used": 65.6732063293457
        }
    },
    "gpu": "NVIDIA GeForce RTX 4070 Ti SUPER",
    "gpu_count": 1,
    "gpu_devices": [
        {
            "name": "NVIDIA GeForce RTX 4070 Ti SUPER",
            "memory_total": 17171480576
        }
    ],
    "memory": {
        "total": 31.165729522705078
    }
}
